nio/__init__.py
nio/_compat.py
nio/api.py
nio/exceptions.py
nio/http.py
nio/monitors.py
nio/responses.py
nio/rooms.py
nio/schemas.py
nio/client/__init__.py
nio/client/async_client.py
nio/client/base_client.py
nio/client/http_client.py
nio/crypto/__init__.py
nio/crypto/async_attachments.py
nio/crypto/attachments.py
nio/crypto/device.py
nio/crypto/key_export.py
nio/crypto/key_request.py
nio/crypto/log.py
nio/crypto/memorystores.py
nio/crypto/olm_machine.py
nio/crypto/sas.py
nio/crypto/sessions.py
nio/event_builders/__init__.py
nio/event_builders/direct_messages.py
nio/event_builders/event_builder.py
nio/event_builders/state_events.py
nio/events/__init__.py
nio/events/account_data.py
nio/events/common.py
nio/events/ephemeral.py
nio/events/invite_events.py
nio/events/misc.py
nio/events/presence.py
nio/events/room_events.py
nio/events/to_device.py
nio/store/__init__.py
nio/store/database.py
nio/store/file_trustdb.py
nio/store/log.py
nio/store/models.py
matrix_nio-0.25.1.dist-info/LICENSE.md
matrix_nio-0.25.1.dist-info/METADATA
matrix_nio-0.25.1.dist-info/WHEEL
matrix_nio-0.25.1.dist-info/top_level.txt
matrix_nio-0.25.1.dist-info/RECORD
