Metadata-Version: 2.1
Name: matrix-nio
Version: 0.25.1
Summary: A Python Matrix client library, designed according to sans I/O principles.
Author-email: Damir Jelić <poljar@termina.org.uk>, Paarth Shah <mail@shahpaarth.com>
License: Internet Systems Consortium license
Project-URL: Source, https://github.com/matrix-nio/matrix-nio
Project-URL: Documentation, https://matrix-nio.readthedocs.io/en/latest/
Requires-Python: >=3.8.0
License-File: LICENSE.md
Requires-Dist: aiohttp ~=3.10
Requires-Dist: aiofiles ~=24.1
Requires-Dist: h11 ~=0.14
Requires-Dist: h2 ~=4.0
Requires-Dist: jsonschema ~=4.14
Requires-Dist: unpaddedbase64 ~=2.1
Requires-Dist: pycryptodome ~=3.10
Requires-Dist: aiohttp-socks ~=0.8
Provides-Extra: dev
Requires-Dist: matrix-nio[e2e] ; extra == 'dev'
Requires-Dist: aioresponses ~=0.7 ; extra == 'dev'
Requires-Dist: hpack ~=4.0 ; extra == 'dev'
Requires-Dist: hyperframe ~=6.0 ; extra == 'dev'
Requires-Dist: hypothesis ~=6.8 ; extra == 'dev'
Requires-Dist: faker ~=8.0 ; extra == 'dev'
Requires-Dist: mypy ~=1.11 ; extra == 'dev'
Requires-Dist: mypy-extensions ~=1.0 ; extra == 'dev'
Requires-Dist: pre-commit ; extra == 'dev'
Requires-Dist: pytest ~=8.2 ; extra == 'dev'
Requires-Dist: pytest-asyncio ~=0.24 ; extra == 'dev'
Requires-Dist: pytest-aiohttp ~=0.3 ; extra == 'dev'
Requires-Dist: pytest-benchmark ~=4.0 ; extra == 'dev'
Requires-Dist: pytest-cov ~=2.11 ; extra == 'dev'
Requires-Dist: pytest-flake8 ~=1.2 ; extra == 'dev'
Provides-Extra: docs
Requires-Dist: matrix-nio[dev] ; extra == 'docs'
Requires-Dist: setuptools >=61.0 ; extra == 'docs'
Requires-Dist: sphinx ~=7.4 ; extra == 'docs'
Requires-Dist: sphinx-autodoc-typehints ~=2.1 ; extra == 'docs'
Requires-Dist: m2r2 ~=0.3 ; extra == 'docs'
Requires-Dist: sphinx-rtd-theme ~=2.0 ; extra == 'docs'
Provides-Extra: e2e
Requires-Dist: atomicwrites ~=1.4 ; extra == 'e2e'
Requires-Dist: cachetools ~=5.3 ; extra == 'e2e'
Requires-Dist: peewee ~=3.14 ; extra == 'e2e'
Requires-Dist: python-olm ~=3.2 ; extra == 'e2e'
